nidhoggr_requests/__init__.py
nidhoggr_requests/core.py
nidhoggr_requests/textures.py
nidhoggr_requests/users.py
tests/__init__.py
tests/conftest.py
tests/test_requests.py
nidhoggr_requests-0.6.0.dist-info/LICENSE
nidhoggr_requests-0.6.0.dist-info/METADATA
nidhoggr_requests-0.6.0.dist-info/WHEEL
nidhoggr_requests-0.6.0.dist-info/top_level.txt
nidhoggr_requests-0.6.0.dist-info/RECORD
