Metadata-Version: 2.1
Name: nidhoggr-requests
Version: 0.6.0
Summary: Requests-based repository implementation for nidhoggr
Home-page: https://git.mc4ep.org/mc4ep/nidhoggr-requests
Author: Roman Shishkin
Author-email: spark@uwtech.org
License: MIT
Keywords: Minecraft,Yggdrasil,Authentication,Nidhoggr
Platform: UNKNOWN
Classifier: Development Status :: 4 - Beta
Classifier: Environment :: No Input/Output (Daemon)
Classifier: Intended Audience :: Developers
Classifier: Intended Audience :: System Administrators
Classifier: License :: OSI Approved
Classifier: License :: OSI Approved :: MIT License
Classifier: Operating System :: OS Independent
Classifier: Programming Language :: Python
Classifier: Programming Language :: Python :: 3
Classifier: Programming Language :: Python :: 3.6
Classifier: Programming Language :: Python :: 3.7
Classifier: Programming Language :: Python :: Implementation :: CPython
Classifier: Programming Language :: Python :: Implementation :: PyPy
Classifier: Topic :: Internet :: WWW/HTTP :: WSGI
Classifier: Topic :: Internet :: WWW/HTTP :: WSGI :: Application
Classifier: Topic :: Utilities
Requires-Dist: nidhoggr-core (>=0.5)
Requires-Dist: requests (>=2.22)
